noobna/__init__.py
noobna/noobna.py
pynoobna-0.0.1.dist-info/LICENSE.md
pynoobna-0.0.1.dist-info/METADATA
pynoobna-0.0.1.dist-info/WHEEL
pynoobna-0.0.1.dist-info/top_level.txt
pynoobna-0.0.1.dist-info/RECORD
