Metadata-Version: 2.1
Name: pynoobna
Version: 0.0.1
Summary: less dumb binary format for nd-array of floats with unitful dimensions
Home-page: UNKNOWN
Author: noobermin
Author-email: ngirmang@protonmail.com
License: MIT
Platform: UNKNOWN
Requires-Dist: numpy (>=1.10.4)
Requires-Dist: docopt (>=0.6.2)
